{
    "@class": "com.kony.gen.viz.model.component.KVizButton",
    "DNDConfig": null,
    "_height_": {
        "type": "string",
        "value": "44dp"
    },
    "_left_": {
        "type": "string",
        "value": "77dp"
    },
    "_margin_": [
        6,
        6,
        6,
        6
    ],
    "_padding_": [
        0,
        0,
        0,
        0
    ],
    "_skin_": "sa41518161404062bfdc0f2e5396c860",
    "_text_": "👏🏻  Add Drink",
    "_top_": {
        "type": "string",
        "value": "687dp"
    },
    "_width_": {
        "type": "string",
        "value": "213dp"
    },
    "canUpdateUI": true,
    "containerweight": 100,
    "contentalignment": 5,
    "displaytext": true,
    "focusskin": "s0b3dd7a70f946beb23b2724e23da200",
    "id": "addDrinkButton",
    "info": null,
    "iscustomlayout": false,
    "isvisible": true,
    "kuid": "f411c9f3a48c4fd1b7e80061f77a0324",
    "name": "kony.ui.Button",
    "parent": "waterTracker",
    "pf": "waterTracker",
    "retaincontentalignment": false,
    "retainflexpositionproperties": false,
    "wType": "Button",
    "zindex": 4
}